svgterm/__init__.py
svgterm/__main__.py
svgterm/anim.py
svgterm/asciicast.py
svgterm/config.py
svgterm/main.py
svgterm/term.py
svgterm/data/svg11-flat-20110816.dtd
svgterm/data/templates/base16_default_dark.svg
svgterm/data/templates/dracula.svg
svgterm/data/templates/gjm8.svg
svgterm/data/templates/gjm8_play.svg
svgterm/data/templates/gjm8_single_loop.svg
svgterm/data/templates/powershell.svg
svgterm/data/templates/progress_bar.svg
svgterm/data/templates/putty.svg
svgterm/data/templates/solarized_dark.svg
svgterm/data/templates/solarized_light.svg
svgterm/data/templates/terminal_app.svg
svgterm/data/templates/ubuntu.svg
svgterm/data/templates/window_frame.svg
svgterm/data/templates/window_frame_js.svg
svgterm/data/templates/window_frame_powershell.svg
svgterm/data/templates/xterm.svg
svgterm/tests/__init__.py
svgterm/tests/suite.py
svgterm/tests/test_anim.py
svgterm/tests/test_asciicast.py
svgterm/tests/test_config.py
svgterm/tests/test_main.py
svgterm/tests/test_term.py
svgterm-1.1.0.data/scripts/svgterm
svgterm-1.1.0.dist-info/LICENSE
svgterm-1.1.0.dist-info/METADATA
svgterm-1.1.0.dist-info/WHEEL
svgterm-1.1.0.dist-info/top_level.txt
svgterm-1.1.0.dist-info/RECORD
